pytv/Converter.py
pytv/ModuleLoader.py
pytv/__init__.py
pytv/utils.py
py4veri_new-0.1.dist-info/LICENSE
py4veri_new-0.1.dist-info/METADATA
py4veri_new-0.1.dist-info/WHEEL
py4veri_new-0.1.dist-info/top_level.txt
py4veri_new-0.1.dist-info/RECORD
